odoo9_addon_product_dimension-9.0.1.1.0-py2.7-nspkg.pth
odoo9_addon_product_dimension-9.0.1.1.0.dist-info/DESCRIPTION.rst
odoo9_addon_product_dimension-9.0.1.1.0.dist-info/METADATA
odoo9_addon_product_dimension-9.0.1.1.0.dist-info/RECORD
odoo9_addon_product_dimension-9.0.1.1.0.dist-info/WHEEL
odoo9_addon_product_dimension-9.0.1.1.0.dist-info/metadata.json
odoo9_addon_product_dimension-9.0.1.1.0.dist-info/namespace_packages.txt
odoo9_addon_product_dimension-9.0.1.1.0.dist-info/top_level.txt
odoo_addons/product_dimension/README.rst
odoo_addons/product_dimension/__init__.py
odoo_addons/product_dimension/__openerp__.py
odoo_addons/product_dimension/i18n/ca.po
odoo_addons/product_dimension/i18n/de.po
odoo_addons/product_dimension/i18n/es.po
odoo_addons/product_dimension/i18n/fr.po
odoo_addons/product_dimension/i18n/fr_FR.po
odoo_addons/product_dimension/models/__init__.py
odoo_addons/product_dimension/models/product.py
odoo_addons/product_dimension/static/description/icon.png
odoo_addons/product_dimension/tests/__init__.py
odoo_addons/product_dimension/tests/test_compute_volume.py
odoo_addons/product_dimension/views/product_view.xml
